README.md
setup.py
xslearn/__init__.py
xslearn.egg-info/PKG-INFO
xslearn.egg-info/SOURCES.txt
xslearn.egg-info/dependency_links.txt
xslearn.egg-info/requires.txt
xslearn.egg-info/top_level.txt
xslearn/models/__init__.py
xslearn/models/base.py
xslearn/models/ensemble.py
xslearn/models/linear_model.py
xslearn/models/naive_bayes.py
xslearn/models/neighbors.py
xslearn/models/svm.py
xslearn/models/tree.py
xslearn/utils/__init__.py
xslearn/utils/split.py
xslearn/utils/toolkit.py